TkPdfWidget/TkPdfWidget.py
TkPdfWidget/__init__.py
TkPdfWidget/icons.png
tkpdfwidget-1.0.dist-info/licenses/LICENCE
tkpdfwidget-1.0.dist-info/METADATA
tkpdfwidget-1.0.dist-info/WHEEL
tkpdfwidget-1.0.dist-info/top_level.txt
tkpdfwidget-1.0.dist-info/RECORD
