Metadata-Version: 2.4
Name: TkPdfWidget
Version: 1.0
Summary: A Pdf file reader in a tkinter's Frame, behaving like a widget
Author-email: "Louis \"Itreza\" Bossy" <louis.bossy@etu.univ-tours.fr>
License-Expression: MIT
Keywords: tkinter,pdf,widget
Classifier: Programming Language :: Python :: 3
Requires-Python: >=3.8
License-File: LICENCE
Requires-Dist: pymupdf
Requires-Dist: pillow
Dynamic: license-file
